a2y_huazhuang/__init__.py
a2y_huazhuang-0.9.dist-info/LICENSE
a2y_huazhuang-0.9.dist-info/METADATA
a2y_huazhuang-0.9.dist-info/WHEEL
a2y_huazhuang-0.9.dist-info/top_level.txt
a2y_huazhuang-0.9.dist-info/RECORD
