Metadata-Version: 2.1
Name: a2y-huazhuang
Version: 0.9
Summary: A module that interfaces DongGuan HuaZhuang Electric things.
Home-page: http://www.sorobust.com/a2y/huazhuang.html
Author: Yu Han
Author-email: hanjunyu@163.com
License: Private
Platform: Windows
Platform: Linux
Classifier: Development Status :: 4 - Beta
Classifier: Intended Audience :: Developers
Classifier: License :: Free For Educational Use
Classifier: Programming Language :: Python :: 3.5
Classifier: Operating System :: Microsoft :: Windows :: Windows 10
Classifier: Operating System :: POSIX :: Linux
Requires-Dist: requests (>=2.25.0)
